polish_salary_calc/__init__.py
polish_salary_calc/contract_settings/__init__.py
polish_salary_calc/contract_settings/contract_settings.py
polish_salary_calc/contract_settings/employment_contract_settings.py
polish_salary_calc/contract_settings/mandate_contract_settings.py
polish_salary_calc/contract_settings/self_employment_settings.py
polish_salary_calc/contract_settings/work_contract_settings.py
polish_salary_calc/contracts/__init__.py
polish_salary_calc/contracts/base_contract.py
polish_salary_calc/contracts/employment_contract.py
polish_salary_calc/contracts/mandate_contract.py
polish_salary_calc/contracts/self_employment.py
polish_salary_calc/contracts/work_contract.py
"polish_salary_calc/Documentation/ChatGPT Image 11 lis 2025, 11_47_29.png"
polish_salary_calc/Documentation/diagram.txt
polish_salary_calc/rates/__init__.py
polish_salary_calc/rates/rates.py
polish_salary_calc/salary/__init__.py
polish_salary_calc/salary/salary.py
polish_salary_calc/salary/salary_utilities.py
polish_salary_calc/salary/salaryexporter.py
polish_salary_calc/summary/__init__.py
polish_salary_calc/summary/contract_summary.py
polish_salary_calc-0.1.2.dist-info/LICENSE
polish_salary_calc-0.1.2.dist-info/METADATA
polish_salary_calc-0.1.2.dist-info/WHEEL
polish_salary_calc-0.1.2.dist-info/RECORD
