Metadata-Version: 2.3
Name: polish-salary-calc
Version: 0.1.2
Summary: Polish salary calculator
License: Free
Author: Jarosław Jezierczak
Author-email: jezierczak@gmail.com
Requires-Python: >=3.12,<4.0
Classifier: License :: Other/Proprietary License
Classifier: Programming Language :: Python :: 3
Classifier: Programming Language :: Python :: 3.12
Classifier: Programming Language :: Python :: 3.13
Requires-Dist: openpyxl (>=3.1.5,<4.0.0)
Requires-Dist: pandas (>=2.3.3,<3.0.0)
